pandis/__init__.py
pandis/client.py
pandis/exceptions.py
pandis/data_structures/__init__.py
pandis/data_structures/base.py
pandis/data_structures/hashes.py
pandis/data_structures/lists.py
pandis/data_structures/sets.py
pandis/data_structures/sorted_sets.py
pandis/data_structures/strings.py
tests/__init__.py
tests/test_hashes.py
tests/test_lists.py
tests/test_sets.py
tests/test_stored_sets.py
tests/test_strings.py
Pandis-1.0.2.dist-info/METADATA
Pandis-1.0.2.dist-info/WHEEL
Pandis-1.0.2.dist-info/top_level.txt
Pandis-1.0.2.dist-info/RECORD
